ezgooey/__init__.py
ezgooey/ez.py
ezgooey/logging.py
ezgooey-1.3.4.dist-info/LICENSE
ezgooey-1.3.4.dist-info/METADATA
ezgooey-1.3.4.dist-info/WHEEL
ezgooey-1.3.4.dist-info/top_level.txt
ezgooey-1.3.4.dist-info/RECORD
