Metadata-Version: 2.1
Name: ezgooey
Version: 1.3.4
Summary: Simplifies making GUI+CLI apps with Gooey
Home-page: https://twardoch.github.io/ezgooey/
Author: Adam Twardoch
Author-email: adam+github@twardoch.com
License: MIT
Project-URL: Source, https://github.com/twardoch/ezgooey/
Keywords: gooey gui cli
Platform: UNKNOWN
Classifier: Development Status :: 4 - Beta
Classifier: License :: OSI Approved :: MIT License
Classifier: Programming Language :: Python :: 3.9
Requires-Python: >=3.8
Requires-Dist: Gooey (>=1.0.8)
Requires-Dist: colored (>=1.4.2)
Provides-Extra: dev
Requires-Dist: twine (>=3.2.0) ; extra == 'dev'
